{"name":"Default","lights":[{"name":"Three directional lights","lights":[{"type":"Ambient","name":"Ambient","intensity":1,"colour":"#050505"},{"type":"Directional","name":"Directional 1","intensity":2.4,"colour":"#ffffff","position":{"X":-0.043,"Y":1.862,"Z":1.90},"target":{"X":0,"Y":0,"Z":1.606}},{"type":"Directional","name":"Directional 2","intensity":2.2,"colour":"#ffffff","position":{"X":-1.569,"Y":-1,"Z":-0.947},"target":{"X":0,"Y":0,"Z":0}},{"type":"Directional","name":"Directional 3","intensity":0.4,"colour":"#ffffff","position":{"X":1.735,"Y":-2.519,"Z":1.266},"target":{"X":0,"Y":0,"Z":0},"castShadow":false}]},{"name":"Ambient","lights":[{"type":"Ambient","name":"Ambient","intensity":0.2,"colour":"#ffffff"}]},{"name":"Directional","lights":[{"type":"Directional","name":"Directional","intensity":2.8,"colour":"#ffffff","position":{"X":2.068,"Y":-1.316,"Z":1.771},"target":{"X":0,"Y":0,"Z":0},"castShadow":false}]},{"name":"Spotlight","lights":[{"type":"Spot","name":"Spotlight","intensity":6400,"colour":"#ffffff","position":{"X":1.076,"Y":-1.471,"Z":1},"target":{"X":0,"Y":0,"Z":0},"castShadow":false,"angle":0.416,"decay":1,"penumbra":0.57,"distance":0}]},{"name":"Point light","lights":[{"type":"Point","name":"Point","intensity":10400,"colour":"#ffffff","position":{"X":0.433,"Y":-0.932,"Z":0.324},"castShadow":false,"decay":1,"distance":0}]}],"current":0}